tengu/__init__.py
tengu/app.py
tengu/backend.py
tengu/cli.py
tengu/config.py
tengu/factory.py
tengu/helpers.py
tengu/models.py
tengu/views.py
tengu-0.1.22.dist-info/AUTHORS.rst
tengu-0.1.22.dist-info/LICENSE
tengu-0.1.22.dist-info/METADATA
tengu-0.1.22.dist-info/WHEEL
tengu-0.1.22.dist-info/entry_points.txt
tengu-0.1.22.dist-info/top_level.txt
tengu-0.1.22.dist-info/RECORD
