Metadata-Version: 2.1
Name: tengu
Version: 0.1.22
Summary: Tengu is an OpenBalkans node implementation
Home-page: https://github.com/openbalkans/tengu
Author: Barak Avrahami
Author-email: barak1345@gmail.com
License: MIT license
Keywords: tengu
Platform: UNKNOWN
Classifier: Development Status :: 2 - Pre-Alpha
Classifier: Intended Audience :: Developers
Classifier: License :: OSI Approved :: MIT License
Classifier: Natural Language :: English
Classifier: Programming Language :: Python :: 3
Classifier: Programming Language :: Python :: 3.4
Classifier: Programming Language :: Python :: 3.5
Classifier: Programming Language :: Python :: 3.6
Classifier: Programming Language :: Python :: 3.7
Requires-Python: >=3
Requires-Dist: flask-sqlalchemy
Requires-Dist: flask
Requires-Dist: schedule
Requires-Dist: uvicorn
Requires-Dist: fastapi
